vertosemver/__init__.py
ver_to_semver-0.1.3.dist-info/METADATA
ver_to_semver-0.1.3.dist-info/WHEEL
ver_to_semver-0.1.3.dist-info/RECORD
