Metadata-Version: 2.1
Name: ver-to-semver
Version: 0.1.3
Summary: Convert any version string to a semver string
Author-email: Maciej Błędkowski <pub@mble.dk>
